sophontool-0.0.2.data/scripts/main.py
stool/__init__.py
stool/__main__.py
stool/main.py
sophontool-0.0.2.dist-info/METADATA
sophontool-0.0.2.dist-info/WHEEL
sophontool-0.0.2.dist-info/entry_points.txt
sophontool-0.0.2.dist-info/top_level.txt
sophontool-0.0.2.dist-info/RECORD
