Metadata-Version: 2.1
Name: sophontool
Version: 0.0.2
Summary: tools for sophon
Home-page: UNKNOWN
Author: yifei.gao, wangyang.zuo
Author-email: yifei.gao@sophgo.com, wangyang.zuo@sophon.com
License: UNKNOWN
Platform: UNKNOWN
Requires-Dist: requests
Requires-Dist: tqdm
Requires-Dist: pycrypto
